django_fileprovider-0.1a3.dist-info/DESCRIPTION.rst
django_fileprovider-0.1a3.dist-info/METADATA
django_fileprovider-0.1a3.dist-info/RECORD
django_fileprovider-0.1a3.dist-info/WHEEL
django_fileprovider-0.1a3.dist-info/metadata.json
django_fileprovider-0.1a3.dist-info/top_level.txt
fileprovider/__init__.py
fileprovider/admin.py
fileprovider/apps.py
fileprovider/decorators.py
fileprovider/middleware.py
fileprovider/models.py
fileprovider/tests.py
fileprovider/utils.py
fileprovider/views.py
