Metadata-Version: 2.0
Name: django-fileprovider
Version: 0.1a3
Summary: django middleware for serving media files
Home-page: https://bitbucket.org/renlinx007/django-file-provider
Author: Renjith Thankachan
Author-email: mail3renjith@gmail.com
License: UNKNOWN
Download-URL: https://bitbucket.org/renlinx007/django-fileprovider/get/0.1a3.tar.gz
Platform: UNKNOWN
Classifier: Environment :: Web Environment
Classifier: Framework :: Django
Classifier: Intended Audience :: Developers
Classifier: License :: OSI Approved :: BSD License
Classifier: Operating System :: OS Independent
Classifier: Programming Language :: Python
Classifier: Programming Language :: Python :: 2
Classifier: Topic :: Utilities
